sdflex_ironic_driver/__init__.py
sdflex_ironic_driver/exception.py
sdflex_ironic_driver/http_utils.py
sdflex_ironic_driver/uefi_http_boot_config.template
sdflex_ironic_driver/version.py
sdflex_ironic_driver/sdflex_redfish/__init__.py
sdflex_ironic_driver/sdflex_redfish/bios.py
sdflex_ironic_driver/sdflex_redfish/boot.py
sdflex_ironic_driver/sdflex_redfish/common.py
sdflex_ironic_driver/sdflex_redfish/deploy.py
sdflex_ironic_driver/sdflex_redfish/drivers.py
sdflex_ironic_driver/sdflex_redfish/firmware_processor.py
sdflex_ironic_driver/sdflex_redfish/management.py
sdflex_ironic_driver/sdflex_redfish/power.py
sdflex_ironic_driver/sdflex_redfish/vendor.py
sdflex_ironic_driver/tests/__init__.py
sdflex_ironic_driver/tests/templates/http_grub_config.template
sdflex_ironic_driver/tests/unit/__init__.py
sdflex_ironic_driver/tests/unit/test_http_utils.py
sdflex_ironic_driver/tests/unit/db/utils.py
sdflex_ironic_driver/tests/unit/objects/utils.py
sdflex_ironic_driver/tests/unit/sdflex_redfish/__init__.py
sdflex_ironic_driver/tests/unit/sdflex_redfish/test_boot.py
sdflex_ironic_driver/tests/unit/sdflex_redfish/test_common.py
sdflex_ironic_driver/tests/unit/sdflex_redfish/test_deploy.py
sdflex_ironic_driver/tests/unit/sdflex_redfish/test_firmware_processor.py
sdflex_ironic_driver/tests/unit/sdflex_redfish/test_management.py
sdflex_ironic_driver/tests/unit/sdflex_redfish/test_vendor.py
sdflex_ironic_driver-1.5.1.dist-info/AUTHORS
sdflex_ironic_driver-1.5.1.dist-info/LICENSE
sdflex_ironic_driver-1.5.1.dist-info/METADATA
sdflex_ironic_driver-1.5.1.dist-info/WHEEL
sdflex_ironic_driver-1.5.1.dist-info/entry_points.txt
sdflex_ironic_driver-1.5.1.dist-info/pbr.json
sdflex_ironic_driver-1.5.1.dist-info/top_level.txt
sdflex_ironic_driver-1.5.1.dist-info/RECORD
