Metadata-Version: 2.1
Name: sdflex-ironic-driver
Version: 1.5.1
Summary: sdflex-ironic-driver provides additional ironic features to manage the Superdome Flex Servers
Home-page: https://github.com/HewlettPackard/sdflex-ironic-driver/wiki
Author: Hewlett Packard Enterprise
Author-email: sdflex.openstack@hpe.com
Classifier: Environment :: OpenStack
Classifier: Intended Audience :: Information Technology
Classifier: Intended Audience :: System Administrators
Classifier: License :: OSI Approved :: Apache Software License
Classifier: Operating System :: POSIX :: Linux
Classifier: Programming Language :: Python
Classifier: Programming Language :: Python :: 3
Classifier: Programming Language :: Python :: 3.5
License-File: LICENSE
License-File: AUTHORS
Requires-Dist: sdflexutils (>=1.5.1)
